xclientai/__about__.py
xclientai/__init__.py
xclientai/config.py
xclientai/benchmarks/__init__.py
xclientai/benchmarks/benchmarks.py
xclientai/cli/__init__.py
xclientai/cli/configure.py
xclientai/clients/__init__.py
xclientai/clients/acceleration_jobs.py
xclientai/clients/deployments.py
xclientai/clients/executor_jobs.py
xclientai/dtypes/__init__.py
xclientai/dtypes/deployments.py
xclientai/dtypes/executor.py
xclientai/dtypes/optimization.py
xclientai/dtypes/shared.py
xclientai/inference_utils/__init__.py
xclientai/inference_utils/inference_utils.py
xclientai/utils/__init__.py
xclientai/utils/config_utils.py
xclientai/utils/logging.py
xclientai/utils/requests_utils.py
xclientai/utils/validations.py
xclientai/utils/zip_files.py
xclientai-0.0.9.dist-info/METADATA
xclientai-0.0.9.dist-info/WHEEL
xclientai-0.0.9.dist-info/entry_points.txt
xclientai-0.0.9.dist-info/top_level.txt
xclientai-0.0.9.dist-info/RECORD
