Metadata-Version: 2.1
Name: xclientai
Version: 0.0.9
Summary: UNKNOWN
Home-page: 
Author: Marcos Rivera Martínez, Sarthak Langde, Glenn Ko, Subhash G N, Toan Do, Roman Ageev
Author-email: marcos.rm@stochastic.ai, sarthak.langde@stochastic.ai, glenn@stochastic.ai, subhash.gn@stochastic.ai
License: UNKNOWN
Platform: UNKNOWN
Classifier: Programming Language :: Python :: 3
Classifier: Operating System :: OS Independent
Requires-Python: >=3.6
Requires-Dist: setuptools
Requires-Dist: pydantic
Requires-Dist: numpy
Requires-Dist: requests
Requires-Dist: python-dotenv
Requires-Dist: kserve
Requires-Dist: click
